{
	"timestamp": "2023-05-26T02:39:34.304Z",
	"bosses": [
		{
			"name": "Zomba",
			"chance": 39.2
		},
		{
			"name": "Zevelon Duskbringer",
			"chance": 38.07
		},
		{
			"name": "General Murius",
			"chance": 33.67,
			"killed": true
		},
		{
			"name": "Man in the Cave",
			"chance": 23.5
		},
		{
			"name": "Big Boss Trolliver",
			"chance": 19.7,
			"killed": true
		},
		{
			"name": "Countess Sorrow",
			"chance": 16.82
		},
		{
			"name": "The Frog Prince",
			"chance": 16.68
		},
		{
			"name": "The Old Whopper",
			"chance": 13.33,
			"killed": true
		},
		{
			"name": "Chizzoron the Distorter",
			"chance": 12.05
		},
		{
			"name": "Zulazza the Corruptor",
			"chance": 12.04
		},
		{
			"name": "Zushuka",
			"chance": 9.75
		},
		{
			"name": "Foreman Kneebiter",
			"chance": 9.68
		},
		{
			"name": "Tyrn",
			"chance": 7.89,
			"killed": true
		},
		{
			"name": "The Evil Eye",
			"chance": 7.37
		},
		{
			"name": "Mr. Punish",
			"chance": 7.02
		},
		{
			"name": "Fleabringer",
			"chance": 6.53
		},
		{
			"name": "Shlorg",
			"chance": 6.47
		},
		{
			"name": "Tzumrah the Dazzler",
			"chance": 6.41
		},
		{
			"name": "White Pale",
			"chance": 6.29
		},
		{
			"name": "Battlemaster Zunzu",
			"chance": 5.86
		},
		{
			"name": "Xenia",
			"chance": 5.71
		},
		{
			"name": "The Voice of Ruin",
			"chance": 3.41
		},
		{
			"name": "Hirintror",
			"chance": 2.9
		},
		{
			"name": "Dreadmaw",
			"chance": 2.46
		},
		{
			"name": "Flamecaller Zazrak",
			"chance": 2.11
		},
		{
			"name": "Morshabaal",
			"chance": 1.61
		}
	]
}
