{
	"timestamp": "2024-10-08T03:42:18.748Z",
	"bosses": [
		{
			"name": "Ocyakao",
			"chance": 67.34
		},
		{
			"name": "General Murius",
			"chance": 53.3
		},
		{
			"name": "Zevelon Duskbringer",
			"chance": 38.56
		},
		{
			"name": "The Plasmother",
			"chance": 36.75
		},
		{
			"name": "Warlord Ruzad",
			"chance": 20.81,
			"killed": true
		},
		{
			"name": "The Blightfather",
			"chance": 18.55
		},
		{
			"name": "Captain Jones",
			"chance": 17.92
		},
		{
			"name": "Rukor Zad",
			"chance": 16.99
		},
		{
			"name": "Omrafir",
			"chance": 16.93
		},
		{
			"name": "midnight panther",
			"chance": 16.56
		},
		{
			"name": "Big Boss Trolliver",
			"chance": 16.27
		},
		{
			"name": "Hairman the Huge",
			"chance": 15.93
		},
		{
			"name": "Foreman Kneebiter",
			"chance": 13.44,
			"killed": true
		},
		{
			"name": "The Imperor",
			"chance": 13.12
		},
		{
			"name": "Fleabringer",
			"chance": 11.61
		},
		{
			"name": "Hatebreeder",
			"chance": 10.53
		},
		{
			"name": "Hirintror",
			"chance": 10.07
		},
		{
			"name": "Zomba",
			"chance": 9.19
		},
		{
			"name": "White Pale",
			"chance": 9.15
		},
		{
			"name": "Zulazza the Corruptor",
			"chance": 8.62
		},
		{
			"name": "Chizzoron the Distorter",
			"chance": 8.61
		},
		{
			"name": "Tyrn",
			"chance": 6.43
		},
		{
			"name": "Flamecaller Zazrak",
			"chance": 6.08
		},
		{
			"name": "The Handmaiden",
			"chance": 6.03
		},
		{
			"name": "Battlemaster Zunzu",
			"chance": 4.95
		},
		{
			"name": "Dreadmaw",
			"chance": 3.94
		},
		{
			"name": "Oodok Witchmaster",
			"chance": 0,
			"killed": true
		},
		{
			"name": "The Mean Masher",
			"chance": 0,
			"killed": true
		}
	]
}
