{
	"timestamp": "2024-02-18T09:31:15.754Z",
	"bosses": [
		{
			"name": "General Murius",
			"chance": 45.68
		},
		{
			"name": "Zarabustor",
			"chance": 31.4
		},
		{
			"name": "The Blightfather",
			"chance": 29.55
		},
		{
			"name": "Dracola",
			"chance": 29.4
		},
		{
			"name": "Big Boss Trolliver",
			"chance": 28.31
		},
		{
			"name": "Willi Wasp",
			"chance": 28.3
		},
		{
			"name": "Grandfather Tridian",
			"chance": 24.91
		},
		{
			"name": "Barbaria",
			"chance": 22.14
		},
		{
			"name": "The Evil Eye",
			"chance": 22.12
		},
		{
			"name": "Zomba",
			"chance": 21.53
		},
		{
			"name": "Arachir the Ancient One",
			"chance": 18.86
		},
		{
			"name": "The Imperor",
			"chance": 18.65
		},
		{
			"name": "Diblis the Fair",
			"chance": 17.33
		},
		{
			"name": "Foreman Kneebiter",
			"chance": 13.89
		},
		{
			"name": "Battlemaster Zunzu",
			"chance": 12.77
		},
		{
			"name": "The Handmaiden",
			"chance": 12.77
		},
		{
			"name": "midnight panther",
			"chance": 12.03
		},
		{
			"name": "Flamecaller Zazrak",
			"chance": 9.38
		},
		{
			"name": "Fleabringer",
			"chance": 8.08
		},
		{
			"name": "White Pale",
			"chance": 8.04
		},
		{
			"name": "Tyrn",
			"chance": 7.31
		},
		{
			"name": "The Old Whopper",
			"chance": 7
		},
		{
			"name": "The Frog Prince",
			"chance": 6.69
		},
		{
			"name": "Xenia",
			"chance": 5.81
		},
		{
			"name": "Hirintror",
			"chance": 3.95
		},
		{
			"name": "The Voice of Ruin",
			"chance": 3.92
		},
		{
			"name": "Dreadmaw",
			"chance": 3.27
		}
	]
}
