{
	"timestamp": "2023-08-04T02:37:12.463Z",
	"bosses": [
		{
			"name": "Arachir the Ancient One",
			"chance": 36.85
		},
		{
			"name": "midnight panther",
			"chance": 29.25
		},
		{
			"name": "Dracola",
			"chance": 28.43
		},
		{
			"name": "The Handmaiden",
			"chance": 25.35,
			"killed": true
		},
		{
			"name": "Countess Sorrow",
			"chance": 23.55
		},
		{
			"name": "Zarabustor",
			"chance": 20.56
		},
		{
			"name": "Hatebreeder",
			"chance": 19.86
		},
		{
			"name": "Zulazza the Corruptor",
			"chance": 18.98
		},
		{
			"name": "Chizzoron the Distorter",
			"chance": 18.97
		},
		{
			"name": "Xenia",
			"chance": 18.33,
			"killed": true
		},
		{
			"name": "Morgaroth",
			"chance": 17.51
		},
		{
			"name": "Smuggler Baron Silvertoe",
			"chance": 17.14
		},
		{
			"name": "Gravelord Oshuran",
			"chance": 16.33
		},
		{
			"name": "Rukor Zad",
			"chance": 15.93,
			"killed": true
		},
		{
			"name": "Hairman the Huge",
			"chance": 15.82
		},
		{
			"name": "Battlemaster Zunzu",
			"chance": 15.65
		},
		{
			"name": "Warlord Ruzad",
			"chance": 14.27,
			"killed": true
		},
		{
			"name": "Ocyakao",
			"chance": 13.91
		},
		{
			"name": "Big Boss Trolliver",
			"chance": 13.76,
			"killed": true
		},
		{
			"name": "Dreadmaw",
			"chance": 11.96
		},
		{
			"name": "Fleabringer",
			"chance": 10.71
		},
		{
			"name": "Diblis the Fair",
			"chance": 9.66
		},
		{
			"name": "Zomba",
			"chance": 9.27
		},
		{
			"name": "The Voice of Ruin",
			"chance": 9.11
		},
		{
			"name": "Shlorg",
			"chance": 8.03
		},
		{
			"name": "The Imperor",
			"chance": 7.41
		},
		{
			"name": "Orshabaal",
			"chance": 6.86
		},
		{
			"name": "Foreman Kneebiter",
			"chance": 6.79
		},
		{
			"name": "White Pale",
			"chance": 6.51
		},
		{
			"name": "The Big Bad One",
			"chance": 6.4
		},
		{
			"name": "yeti",
			"chance": 5.63,
			"killed": true
		},
		{
			"name": "Tyrn",
			"chance": 4.71
		},
		{
			"name": "Hirintror",
			"chance": 3.27
		},
		{
			"name": "Flamecaller Zazrak",
			"chance": 2.89
		},
		{
			"name": "Groam",
			"chance": 0,
			"killed": true
		},
		{
			"name": "High Templar Cobrass",
			"chance": 0,
			"killed": true
		},
		{
			"name": "Yakchal",
			"chance": 0,
			"killed": true
		}
	]
}
