{
	"timestamp": "2024-05-03T09:31:30.896Z",
	"bosses": [
		{
			"name": "The Blightfather",
			"chance": 42.29
		},
		{
			"name": "Arachir the Ancient One",
			"chance": 37.7
		},
		{
			"name": "Yaga the Crone",
			"chance": 33.94
		},
		{
			"name": "General Murius",
			"chance": 33.8
		},
		{
			"name": "Dharalion",
			"chance": 31.93
		},
		{
			"name": "Big Boss Trolliver",
			"chance": 29.04
		},
		{
			"name": "Foreman Kneebiter",
			"chance": 25.47
		},
		{
			"name": "Zarabustor",
			"chance": 24.39
		},
		{
			"name": "Ocyakao",
			"chance": 22.87
		},
		{
			"name": "Gravelord Oshuran",
			"chance": 21.78
		},
		{
			"name": "Grand Mother Foulscale",
			"chance": 21.18
		},
		{
			"name": "Hairman the Huge",
			"chance": 21.11
		},
		{
			"name": "The Big Bad One",
			"chance": 20.5
		},
		{
			"name": "Xenia",
			"chance": 15.9
		},
		{
			"name": "midnight panther",
			"chance": 13.44
		},
		{
			"name": "Battlemaster Zunzu",
			"chance": 12.82
		},
		{
			"name": "The Handmaiden",
			"chance": 12.7
		},
		{
			"name": "Captain Jones",
			"chance": 11.9
		},
		{
			"name": "Shlorg",
			"chance": 11.51
		},
		{
			"name": "Hatebreeder",
			"chance": 10.34
		},
		{
			"name": "Zomba",
			"chance": 9.18
		},
		{
			"name": "The Evil Eye",
			"chance": 8.73
		},
		{
			"name": "Fleabringer",
			"chance": 8.37
		},
		{
			"name": "Rukor Zad",
			"chance": 8.2
		},
		{
			"name": "Tyrn",
			"chance": 8.08
		},
		{
			"name": "The Old Whopper",
			"chance": 6.89
		},
		{
			"name": "Massacre",
			"chance": 6.7
		},
		{
			"name": "White Pale",
			"chance": 6.53
		},
		{
			"name": "The Voice of Ruin",
			"chance": 4.81
		},
		{
			"name": "The Welter",
			"chance": 4.61
		},
		{
			"name": "Dreadmaw",
			"chance": 3.98
		},
		{
			"name": "Hirintror",
			"chance": 3.41
		},
		{
			"name": "Flamecaller Zazrak",
			"chance": 3.07
		}
	]
}
