{
	"timestamp": "2025-03-16T03:40:19.900Z",
	"bosses": [
		{
			"name": "Grand Mother Foulscale",
			"chance": 81.46,
			"killed": true
		},
		{
			"name": "Dharalion",
			"chance": 70.14
		},
		{
			"name": "General Murius",
			"chance": 53.49,
			"killed": true
		},
		{
			"name": "Willi Wasp",
			"chance": 39.84
		},
		{
			"name": "Zomba",
			"chance": 39.45
		},
		{
			"name": "The Imperor",
			"chance": 34.31
		},
		{
			"name": "Tzumrah the Dazzler",
			"chance": 31.41
		},
		{
			"name": "The Big Bad One",
			"chance": 29.62
		},
		{
			"name": "High Templar Cobrass",
			"chance": 29.57
		},
		{
			"name": "Zevelon Duskbringer",
			"chance": 27.61
		},
		{
			"name": "Arachir the Ancient One",
			"chance": 20.95,
			"killed": true
		},
		{
			"name": "Zarabustor",
			"chance": 20
		},
		{
			"name": "Foreman Kneebiter",
			"chance": 19.84
		},
		{
			"name": "The Plasmother",
			"chance": 19.31
		},
		{
			"name": "Hatebreeder",
			"chance": 19.23,
			"killed": true
		},
		{
			"name": "midnight panther",
			"chance": 17.35
		},
		{
			"name": "Big Boss Trolliver",
			"chance": 16.25
		},
		{
			"name": "Shlorg",
			"chance": 15.64
		},
		{
			"name": "The Frog Prince",
			"chance": 13.71
		},
		{
			"name": "Ferumbras",
			"chance": 12.01
		},
		{
			"name": "The Blightfather",
			"chance": 10.65
		},
		{
			"name": "The Pale Count",
			"chance": 10.41
		},
		{
			"name": "White Pale",
			"chance": 8.95
		},
		{
			"name": "Hirintror",
			"chance": 8.79
		},
		{
			"name": "Rukor Zad",
			"chance": 8.36
		},
		{
			"name": "Battlemaster Zunzu",
			"chance": 8.24
		},
		{
			"name": "Fleabringer",
			"chance": 8.03
		},
		{
			"name": "Flamecaller Zazrak",
			"chance": 6.56
		},
		{
			"name": "Tyrn",
			"chance": 6.47,
			"killed": true
		},
		{
			"name": "Dreadmaw",
			"chance": 3.58
		},
		{
			"name": "The Voice of Ruin",
			"chance": 3.28
		},
		{
			"name": "Groam",
			"chance": 0,
			"killed": true
		},
		{
			"name": "Horestis",
			"chance": 0,
			"killed": true
		},
		{
			"name": "Oodok Witchmaster",
			"chance": 0,
			"killed": true
		}
	]
}
