{
	"timestamp": "2026-01-02T09:36:53.943Z",
	"bosses": [
		{
			"name": "Grand Mother Foulscale",
			"chance": 40.33
		},
		{
			"name": "Hatebreeder",
			"chance": 32.69
		},
		{
			"name": "Flamecaller Zazrak",
			"chance": 22.24
		},
		{
			"name": "The Big Bad One",
			"chance": 21.18
		},
		{
			"name": "Willi Wasp",
			"chance": 20.66
		},
		{
			"name": "Zomba",
			"chance": 17.2
		},
		{
			"name": "The Imperor",
			"chance": 16.18
		},
		{
			"name": "Xenia",
			"chance": 15.92
		},
		{
			"name": "Zevelon Duskbringer",
			"chance": 14.09
		},
		{
			"name": "Battlemaster Zunzu",
			"chance": 13.62
		},
		{
			"name": "Foreman Kneebiter",
			"chance": 13.22
		},
		{
			"name": "midnight panther",
			"chance": 12.24
		},
		{
			"name": "Gaz'haragoth",
			"chance": 11.71
		},
		{
			"name": "Gravelord Oshuran",
			"chance": 11.3
		},
		{
			"name": "Smuggler Baron Silvertoe",
			"chance": 10.93
		},
		{
			"name": "Hirintror",
			"chance": 9.28
		},
		{
			"name": "Hairman the Huge",
			"chance": 9.24
		},
		{
			"name": "The Evil Eye",
			"chance": 9.2
		},
		{
			"name": "Rukor Zad",
			"chance": 9.01
		},
		{
			"name": "Fleabringer",
			"chance": 8.97
		},
		{
			"name": "Yaga the Crone",
			"chance": 7.32
		},
		{
			"name": "White Pale",
			"chance": 6.59
		},
		{
			"name": "Shlorg",
			"chance": 6.44
		},
		{
			"name": "Barbaria",
			"chance": 5.77
		},
		{
			"name": "Tyrn",
			"chance": 5.37
		},
		{
			"name": "The Voice of Ruin",
			"chance": 3.32
		},
		{
			"name": "Dreadmaw",
			"chance": 3.07
		}
	]
}
