{
	"timestamp": "2026-01-22T09:41:57.910Z",
	"bosses": [
		{
			"name": "Grand Mother Foulscale",
			"chance": 81.27
		},
		{
			"name": "Yaga the Crone",
			"chance": 36.89
		},
		{
			"name": "Zevelon Duskbringer",
			"chance": 27.64
		},
		{
			"name": "Gaz'haragoth",
			"chance": 25.43
		},
		{
			"name": "Warlord Ruzad",
			"chance": 23.41
		},
		{
			"name": "Zarabustor",
			"chance": 23.2
		},
		{
			"name": "The Handmaiden",
			"chance": 22.32
		},
		{
			"name": "Willi Wasp",
			"chance": 20.65
		},
		{
			"name": "Foreman Kneebiter",
			"chance": 18.81
		},
		{
			"name": "Diblis the Fair",
			"chance": 17.78
		},
		{
			"name": "Dracola",
			"chance": 15.99
		},
		{
			"name": "The Voice of Ruin",
			"chance": 15.94
		},
		{
			"name": "Fleabringer",
			"chance": 13.62
		},
		{
			"name": "The Blightfather",
			"chance": 10.74
		},
		{
			"name": "Zulazza the Corruptor",
			"chance": 10.74
		},
		{
			"name": "Chizzoron the Distorter",
			"chance": 10.71
		},
		{
			"name": "Zomba",
			"chance": 9.18
		},
		{
			"name": "The Welter",
			"chance": 9.14
		},
		{
			"name": "The Big Bad One",
			"chance": 7.64
		},
		{
			"name": "Battlemaster Zunzu",
			"chance": 6.07
		},
		{
			"name": "Tyrn",
			"chance": 5.43
		},
		{
			"name": "Flamecaller Zazrak",
			"chance": 4.34
		},
		{
			"name": "Hirintror",
			"chance": 3.74
		},
		{
			"name": "Dreadmaw",
			"chance": 3.38
		}
	]
}
