{
	"timestamp": "2023-10-29T02:34:22.357Z",
	"bosses": [
		{
			"name": "Xenia",
			"chance": 25.54,
			"killed": true
		},
		{
			"name": "High Templar Cobrass",
			"chance": 22.93
		},
		{
			"name": "Hatebreeder",
			"chance": 20.84
		},
		{
			"name": "The Pale Count",
			"chance": 20.65
		},
		{
			"name": "midnight panther",
			"chance": 17.13
		},
		{
			"name": "Hairman the Huge",
			"chance": 16.01
		},
		{
			"name": "Big Boss Trolliver",
			"chance": 14.97
		},
		{
			"name": "The Voice of Ruin",
			"chance": 14.25
		},
		{
			"name": "Zevelon Duskbringer",
			"chance": 14.19
		},
		{
			"name": "Foreman Kneebiter",
			"chance": 14.03
		},
		{
			"name": "Countess Sorrow",
			"chance": 13.03
		},
		{
			"name": "The Imperor",
			"chance": 12.91
		},
		{
			"name": "Hirintror",
			"chance": 11.5
		},
		{
			"name": "Warlord Ruzad",
			"chance": 10.37,
			"killed": true
		},
		{
			"name": "White Pale",
			"chance": 8.69,
			"killed": true
		},
		{
			"name": "Fleabringer",
			"chance": 7.1
		},
		{
			"name": "Dracola",
			"chance": 6.57
		},
		{
			"name": "Battlemaster Zunzu",
			"chance": 5.17
		},
		{
			"name": "Tyrn",
			"chance": 4.87
		},
		{
			"name": "Flamecaller Zazrak",
			"chance": 2.59
		},
		{
			"name": "Dreadmaw",
			"chance": 1.91
		},
		{
			"name": "Yakchal",
			"chance": 0,
			"killed": true
		}
	]
}
