{
	"timestamp": "2024-07-22T03:33:57.673Z",
	"bosses": [
		{
			"name": "Sir Valorcrest",
			"chance": 42.31,
			"killed": true
		},
		{
			"name": "yeti",
			"chance": 37.87
		},
		{
			"name": "The Voice of Ruin",
			"chance": 33.25
		},
		{
			"name": "Big Boss Trolliver",
			"chance": 29.19
		},
		{
			"name": "midnight panther",
			"chance": 22.83
		},
		{
			"name": "Chizzoron the Distorter",
			"chance": 22.79
		},
		{
			"name": "Zulazza the Corruptor",
			"chance": 22.79
		},
		{
			"name": "Zomba",
			"chance": 21.58
		},
		{
			"name": "Willi Wasp",
			"chance": 20.7
		},
		{
			"name": "Yaga the Crone",
			"chance": 19.7,
			"killed": true
		},
		{
			"name": "Xenia",
			"chance": 18.5
		},
		{
			"name": "Foreman Kneebiter",
			"chance": 17.24,
			"killed": true
		},
		{
			"name": "Zushuka",
			"chance": 13.45,
			"killed": true
		},
		{
			"name": "Hairman the Huge",
			"chance": 12.45
		},
		{
			"name": "Fleabringer",
			"chance": 11.57
		},
		{
			"name": "Flamecaller Zazrak",
			"chance": 11.35
		},
		{
			"name": "High Templar Cobrass",
			"chance": 10.15
		},
		{
			"name": "Diblis the Fair",
			"chance": 9.72
		},
		{
			"name": "Captain Jones",
			"chance": 9.65
		},
		{
			"name": "White Pale",
			"chance": 8.7
		},
		{
			"name": "The Old Whopper",
			"chance": 6.34
		},
		{
			"name": "Battlemaster Zunzu",
			"chance": 5.22
		},
		{
			"name": "Tyrn",
			"chance": 4.85
		},
		{
			"name": "Hirintror",
			"chance": 3.38
		},
		{
			"name": "Dreadmaw",
			"chance": 2.8
		},
		{
			"name": "Omrafir",
			"chance": 0,
			"killed": true
		},
		{
			"name": "Oodok Witchmaster",
			"chance": 0,
			"killed": true
		},
		{
			"name": "Rotworm Queen",
			"chance": 0,
			"killed": true
		},
		{
			"name": "Yakchal",
			"chance": 0,
			"killed": true
		}
	]
}
