{
	"timestamp": "2025-01-29T03:34:17.289Z",
	"bosses": [
		{
			"name": "Hatebreeder",
			"chance": 31.97,
			"killed": true
		},
		{
			"name": "Big Boss Trolliver",
			"chance": 21.83
		},
		{
			"name": "Zomba",
			"chance": 21.75,
			"killed": true
		},
		{
			"name": "Warlord Ruzad",
			"chance": 21.04
		},
		{
			"name": "Willi Wasp",
			"chance": 20.73
		},
		{
			"name": "The Pale Count",
			"chance": 20.54
		},
		{
			"name": "Battlemaster Zunzu",
			"chance": 20.19
		},
		{
			"name": "Arachir the Ancient One",
			"chance": 19.13
		},
		{
			"name": "The Big Bad One",
			"chance": 18.38
		},
		{
			"name": "yeti",
			"chance": 17.84
		},
		{
			"name": "The Frog Prince",
			"chance": 17.07
		},
		{
			"name": "General Murius",
			"chance": 16.96
		},
		{
			"name": "midnight panther",
			"chance": 15.71
		},
		{
			"name": "The Handmaiden",
			"chance": 15.38
		},
		{
			"name": "Foreman Kneebiter",
			"chance": 14.05
		},
		{
			"name": "Omrafir",
			"chance": 8.98
		},
		{
			"name": "Fleabringer",
			"chance": 8.65
		},
		{
			"name": "White Pale",
			"chance": 6.69
		},
		{
			"name": "Tyrn",
			"chance": 5.68
		},
		{
			"name": "Hairman the Huge",
			"chance": 5.4
		},
		{
			"name": "Dreadmaw",
			"chance": 4.98
		},
		{
			"name": "Flamecaller Zazrak",
			"chance": 3.44
		},
		{
			"name": "The Voice of Ruin",
			"chance": 3.26
		},
		{
			"name": "Hirintror",
			"chance": 3.09
		},
		{
			"name": "Yakchal",
			"chance": 0,
			"killed": true
		}
	]
}
