{
	"timestamp": "2022-08-23T08:39:13.537Z",
	"bosses": [
		{
			"name": "Arachir The Ancient One",
			"chance": 55.74
		},
		{
			"name": "Battlemaster Zunzu",
			"chance": 39.57
		},
		{
			"name": "Zevelon Duskbringer",
			"chance": 37.59
		},
		{
			"name": "Mr. Punish",
			"chance": 24.07
		},
		{
			"name": "The Handmaiden",
			"chance": 21.98
		},
		{
			"name": "The Blightfather",
			"chance": 21.87
		},
		{
			"name": "midnight panthers",
			"chance": 16.35
		},
		{
			"name": "Foreman Kneebiter",
			"chance": 14.79
		},
		{
			"name": "yetis",
			"chance": 10.48
		},
		{
			"name": "Zomba",
			"chance": 9.27
		},
		{
			"name": "Dreadmaw",
			"chance": 9.22
		},
		{
			"name": "Fleabringer",
			"chance": 6.6
		},
		{
			"name": "Hairman The Huge",
			"chance": 6.41
		},
		{
			"name": "White Pale",
			"chance": 6.2
		},
		{
			"name": "Zushuka",
			"chance": 5.58
		},
		{
			"name": "Tyrn",
			"chance": 4.88
		},
		{
			"name": "The Voice Of Ruin",
			"chance": 3.33
		},
		{
			"name": "Hirintror",
			"chance": 2.49
		}
	]
}
