{
	"timestamp": "2025-07-04T03:47:22.522Z",
	"bosses": [
		{
			"name": "midnight panther",
			"chance": 65.45
		},
		{
			"name": "High Templar Cobrass",
			"chance": 37.14,
			"killed": true
		},
		{
			"name": "The Frog Prince",
			"chance": 27.48
		},
		{
			"name": "Shlorg",
			"chance": 22.26
		},
		{
			"name": "Warlord Ruzad",
			"chance": 21.58
		},
		{
			"name": "Fleabringer",
			"chance": 18.91
		},
		{
			"name": "Ocyakao",
			"chance": 18.54
		},
		{
			"name": "The Voice of Ruin",
			"chance": 17.03
		},
		{
			"name": "Battlemaster Zunzu",
			"chance": 13.99
		},
		{
			"name": "Zushuka",
			"chance": 13.5
		},
		{
			"name": "The Imperor",
			"chance": 13.11,
			"killed": true
		},
		{
			"name": "Willi Wasp",
			"chance": 11.19
		},
		{
			"name": "The Blightfather",
			"chance": 10.7
		},
		{
			"name": "Zulazza the Corruptor",
			"chance": 10.63
		},
		{
			"name": "Chizzoron the Distorter",
			"chance": 10.6
		},
		{
			"name": "Hirintror",
			"chance": 10
		},
		{
			"name": "Flamecaller Zazrak",
			"chance": 8.41
		},
		{
			"name": "White Pale",
			"chance": 8.3,
			"killed": true
		},
		{
			"name": "Tzumrah the Dazzler",
			"chance": 6.35
		},
		{
			"name": "Tyrn",
			"chance": 4.79
		},
		{
			"name": "Dreadmaw",
			"chance": 2.83
		},
		{
			"name": "Countess Sorrow",
			"chance": 0,
			"killed": true
		}
	]
}
