{
	"timestamp": "2024-09-21T09:36:02.660Z",
	"bosses": [
		{
			"name": "Diblis the Fair",
			"chance": 47.11
		},
		{
			"name": "High Templar Cobrass",
			"chance": 35.65
		},
		{
			"name": "The Blightfather",
			"chance": 30.68
		},
		{
			"name": "The Evil Eye",
			"chance": 29.98
		},
		{
			"name": "Captain Jones",
			"chance": 23.26
		},
		{
			"name": "midnight panther",
			"chance": 22.99
		},
		{
			"name": "Battlemaster Zunzu",
			"chance": 22.17
		},
		{
			"name": "Omrafir",
			"chance": 19.6
		},
		{
			"name": "Zomba",
			"chance": 17.11
		},
		{
			"name": "Tyrn",
			"chance": 16.86
		},
		{
			"name": "Hairman the Huge",
			"chance": 16
		},
		{
			"name": "The Old Whopper",
			"chance": 15.46
		},
		{
			"name": "Xenia",
			"chance": 13.4
		},
		{
			"name": "The Pale Count",
			"chance": 11.26
		},
		{
			"name": "Tzumrah the Dazzler",
			"chance": 11.09
		},
		{
			"name": "White Pale",
			"chance": 9.3
		},
		{
			"name": "Shlorg",
			"chance": 7.76
		},
		{
			"name": "Flamecaller Zazrak",
			"chance": 7.35
		},
		{
			"name": "Dreadmaw",
			"chance": 7
		},
		{
			"name": "Chizzoron the Distorter",
			"chance": 5.45
		},
		{
			"name": "Zulazza the Corruptor",
			"chance": 5.45
		}
	]
}
