{
	"timestamp": "2024-11-11T03:41:18.500Z",
	"bosses": [
		{
			"name": "Battlemaster Zunzu",
			"chance": 47.1
		},
		{
			"name": "Morgaroth",
			"chance": 42.91,
			"killed": true
		},
		{
			"name": "Grand Mother Foulscale",
			"chance": 40.26,
			"killed": true
		},
		{
			"name": "Hairman the Huge",
			"chance": 37.53
		},
		{
			"name": "The Evil Eye",
			"chance": 30.16
		},
		{
			"name": "The Welter",
			"chance": 22.96,
			"killed": true
		},
		{
			"name": "Smuggler Baron Silvertoe",
			"chance": 18.21
		},
		{
			"name": "yeti",
			"chance": 17.77
		},
		{
			"name": "Zomba",
			"chance": 17.05
		},
		{
			"name": "The Old Whopper",
			"chance": 16.7
		},
		{
			"name": "midnight panther",
			"chance": 16.62
		},
		{
			"name": "The Pale Count",
			"chance": 15.39
		},
		{
			"name": "Dracola",
			"chance": 13.54
		},
		{
			"name": "Flamecaller Zazrak",
			"chance": 9.77
		},
		{
			"name": "Fleabringer",
			"chance": 8.44,
			"killed": true
		},
		{
			"name": "The Big Bad One",
			"chance": 7.59
		},
		{
			"name": "Dreadmaw",
			"chance": 3.67
		},
		{
			"name": "draptor",
			"chance": 0,
			"killed": true
		}
	]
}
