{
	"timestamp": "2024-11-25T03:45:32.152Z",
	"bosses": [
		{
			"name": "Zevelon Duskbringer",
			"chance": 61.86,
			"killed": true
		},
		{
			"name": "Diblis the Fair",
			"chance": 29.37
		},
		{
			"name": "The Imperor",
			"chance": 25.77
		},
		{
			"name": "Barbaria",
			"chance": 23.14
		},
		{
			"name": "midnight panther",
			"chance": 23.06,
			"killed": true
		},
		{
			"name": "Grand Mother Foulscale",
			"chance": 21.19,
			"killed": true
		},
		{
			"name": "Chizzoron the Distorter",
			"chance": 19.13
		},
		{
			"name": "Zulazza the Corruptor",
			"chance": 19.12
		},
		{
			"name": "Fleabringer",
			"chance": 13.27
		},
		{
			"name": "Zushuka",
			"chance": 9.71,
			"killed": true
		},
		{
			"name": "Zomba",
			"chance": 9.22
		},
		{
			"name": "Shlorg",
			"chance": 7.74
		},
		{
			"name": "Yaga the Crone",
			"chance": 6.81
		},
		{
			"name": "Tyrn",
			"chance": 6.38
		},
		{
			"name": "Battlemaster Zunzu",
			"chance": 5.53
		},
		{
			"name": "Dreadmaw",
			"chance": 5.45
		},
		{
			"name": "Gravelord Oshuran",
			"chance": 5.12
		},
		{
			"name": "Flamecaller Zazrak",
			"chance": 3.26
		},
		{
			"name": "The Abomination",
			"chance": 3.25
		},
		{
			"name": "Horestis",
			"chance": 0,
			"killed": true
		},
		{
			"name": "The Handmaiden",
			"chance": 0,
			"killed": true
		},
		{
			"name": "draptor",
			"chance": 0,
			"killed": true
		}
	]
}
