{
	"timestamp": "2025-11-04T09:36:11.388Z",
	"bosses": [
		{
			"name": "Grand Mother Foulscale",
			"chance": 65.2
		},
		{
			"name": "Smuggler Baron Silvertoe",
			"chance": 34.9
		},
		{
			"name": "The Handmaiden",
			"chance": 26.77
		},
		{
			"name": "The Imperor",
			"chance": 26.57
		},
		{
			"name": "midnight panther",
			"chance": 23.39
		},
		{
			"name": "The Frog Prince",
			"chance": 20.71
		},
		{
			"name": "Willi Wasp",
			"chance": 20.61
		},
		{
			"name": "The Old Whopper",
			"chance": 18.21
		},
		{
			"name": "Zomba",
			"chance": 17.18
		},
		{
			"name": "Sir Valorcrest",
			"chance": 16.07
		},
		{
			"name": "Tyrn",
			"chance": 15.55
		},
		{
			"name": "Flamecaller Zazrak",
			"chance": 14.48
		},
		{
			"name": "Dreadmaw",
			"chance": 13.5
		},
		{
			"name": "The Big Bad One",
			"chance": 7.68
		},
		{
			"name": "Orshabaal",
			"chance": 7.31
		},
		{
			"name": "White Pale",
			"chance": 6.61
		},
		{
			"name": "Battlemaster Zunzu",
			"chance": 6.04
		},
		{
			"name": "yeti",
			"chance": 5.84
		},
		{
			"name": "Hirintror",
			"chance": 3.68
		}
	]
}
