{
	"timestamp": "2024-01-20T09:31:29.388Z",
	"bosses": [
		{
			"name": "The Handmaiden",
			"chance": 38.5
		},
		{
			"name": "Zarabustor",
			"chance": 29.63
		},
		{
			"name": "Willi Wasp",
			"chance": 28.31
		},
		{
			"name": "The Evil Eye",
			"chance": 27.8
		},
		{
			"name": "The Frog Prince",
			"chance": 23.69
		},
		{
			"name": "midnight panther",
			"chance": 22.61
		},
		{
			"name": "The Big Bad One",
			"chance": 19.8
		},
		{
			"name": "Warlord Ruzad",
			"chance": 19.4
		},
		{
			"name": "Zomba",
			"chance": 17.09
		},
		{
			"name": "Battlemaster Zunzu",
			"chance": 16.52
		},
		{
			"name": "Hatebreeder",
			"chance": 14.56
		},
		{
			"name": "Zevelon Duskbringer",
			"chance": 14.36
		},
		{
			"name": "Xenia",
			"chance": 12.95
		},
		{
			"name": "The Old Whopper",
			"chance": 12.65
		},
		{
			"name": "Dracola",
			"chance": 12.51
		},
		{
			"name": "Grand Mother Foulscale",
			"chance": 11.57
		},
		{
			"name": "Flamecaller Zazrak",
			"chance": 10.99
		},
		{
			"name": "White Pale",
			"chance": 10.14
		},
		{
			"name": "Hairman the Huge",
			"chance": 9.16
		},
		{
			"name": "Tyrn",
			"chance": 8.09
		},
		{
			"name": "Dreadmaw",
			"chance": 7.81
		},
		{
			"name": "Countess Sorrow",
			"chance": 7.13
		},
		{
			"name": "Shlorg",
			"chance": 6.8
		},
		{
			"name": "Hirintror",
			"chance": 3.33
		}
	]
}
