{
	"timestamp": "2024-01-24T03:33:08.674Z",
	"bosses": [
		{
			"name": "Arachir the Ancient One",
			"chance": 37.35,
			"killed": true
		},
		{
			"name": "Yaga the Crone",
			"chance": 33.75
		},
		{
			"name": "Sir Valorcrest",
			"chance": 29.3
		},
		{
			"name": "Grandfather Tridian",
			"chance": 27.99
		},
		{
			"name": "Dracola",
			"chance": 23.09
		},
		{
			"name": "Xenia",
			"chance": 22.23
		},
		{
			"name": "Diblis the Fair",
			"chance": 21.71
		},
		{
			"name": "The Blightfather",
			"chance": 18.26,
			"killed": true
		},
		{
			"name": "midnight panther",
			"chance": 17.21
		},
		{
			"name": "White Pale",
			"chance": 17.21
		},
		{
			"name": "Tyrn",
			"chance": 15.56
		},
		{
			"name": "The Old Whopper",
			"chance": 14.57
		},
		{
			"name": "Hatebreeder",
			"chance": 13.35
		},
		{
			"name": "Mr. Punish",
			"chance": 11.15
		},
		{
			"name": "Shlorg",
			"chance": 8.69
		},
		{
			"name": "Rukor Zad",
			"chance": 8.18
		},
		{
			"name": "Fleabringer",
			"chance": 7.82
		},
		{
			"name": "Smuggler Baron Silvertoe",
			"chance": 6.18
		},
		{
			"name": "Battlemaster Zunzu",
			"chance": 5.2
		},
		{
			"name": "Gravelord Oshuran",
			"chance": 5.2
		},
		{
			"name": "Hirintror",
			"chance": 4.48
		},
		{
			"name": "Flamecaller Zazrak",
			"chance": 3.17
		},
		{
			"name": "Dreadmaw",
			"chance": 3
		},
		{
			"name": "Arthom the Hunter",
			"chance": 0,
			"killed": true
		},
		{
			"name": "Oodok Witchmaster",
			"chance": 0,
			"killed": true
		}
	]
}
