{
	"timestamp": "2024-06-26T09:31:49.713Z",
	"bosses": [
		{
			"name": "Zomba",
			"chance": 62.24
		},
		{
			"name": "Sir Valorcrest",
			"chance": 42.23
		},
		{
			"name": "Diblis the Fair",
			"chance": 41.33
		},
		{
			"name": "Warlord Ruzad",
			"chance": 32.35
		},
		{
			"name": "Grand Mother Foulscale",
			"chance": 28.66
		},
		{
			"name": "midnight panther",
			"chance": 22.79
		},
		{
			"name": "Fleabringer",
			"chance": 22.6
		},
		{
			"name": "Captain Jones",
			"chance": 20.61
		},
		{
			"name": "Countess Sorrow",
			"chance": 16.41
		},
		{
			"name": "Big Boss Trolliver",
			"chance": 16.09
		},
		{
			"name": "Dracola",
			"chance": 15.99
		},
		{
			"name": "Chizzoron the Distorter",
			"chance": 15.41
		},
		{
			"name": "Zulazza the Corruptor",
			"chance": 15.39
		},
		{
			"name": "Gravelord Oshuran",
			"chance": 15.25
		},
		{
			"name": "Zevelon Duskbringer",
			"chance": 14.33
		},
		{
			"name": "The Voice of Ruin",
			"chance": 14.09
		},
		{
			"name": "Omrafir",
			"chance": 11.55
		},
		{
			"name": "Flamecaller Zazrak",
			"chance": 11.33
		},
		{
			"name": "White Pale",
			"chance": 11.19
		},
		{
			"name": "Willi Wasp",
			"chance": 11.14
		},
		{
			"name": "The Old Whopper",
			"chance": 8.85
		},
		{
			"name": "Xenia",
			"chance": 8.85
		},
		{
			"name": "The Imperor",
			"chance": 7.55
		},
		{
			"name": "Battlemaster Zunzu",
			"chance": 6.97
		},
		{
			"name": "Smuggler Baron Silvertoe",
			"chance": 6.09
		},
		{
			"name": "Hirintror",
			"chance": 4.12
		}
	]
}
