{
	"timestamp": "2025-01-25T09:31:36.704Z",
	"bosses": [
		{
			"name": "Zomba",
			"chance": 62.17
		},
		{
			"name": "Sir Valorcrest",
			"chance": 42.3
		},
		{
			"name": "Grand Mother Foulscale",
			"chance": 40.19
		},
		{
			"name": "The Blightfather",
			"chance": 28.46
		},
		{
			"name": "The Handmaiden",
			"chance": 22.73
		},
		{
			"name": "Rukor Zad",
			"chance": 21.4
		},
		{
			"name": "Omrafir",
			"chance": 17.03
		},
		{
			"name": "Massacre",
			"chance": 16.32
		},
		{
			"name": "The Pale Count",
			"chance": 15.55
		},
		{
			"name": "Hirintror",
			"chance": 14.14
		},
		{
			"name": "The Big Bad One",
			"chance": 13.91
		},
		{
			"name": "Dreadmaw",
			"chance": 12.14
		},
		{
			"name": "Fleabringer",
			"chance": 11.29
		},
		{
			"name": "Tzumrah the Dazzler",
			"chance": 11.15
		},
		{
			"name": "Zushuka",
			"chance": 9.64
		},
		{
			"name": "Flamecaller Zazrak",
			"chance": 8.11
		},
		{
			"name": "Tyrn",
			"chance": 6.47
		},
		{
			"name": "The Frog Prince",
			"chance": 6.43
		},
		{
			"name": "Battlemaster Zunzu",
			"chance": 4.88
		},
		{
			"name": "Morshabaal",
			"chance": 3.72
		}
	]
}
