{
	"timestamp": "2025-02-01T03:35:28.281Z",
	"bosses": [
		{
			"name": "Diblis the Fair",
			"chance": 43.32,
			"killed": true
		},
		{
			"name": "Willi Wasp",
			"chance": 39.89,
			"killed": true
		},
		{
			"name": "Zevelon Duskbringer",
			"chance": 38.59
		},
		{
			"name": "Hirintror",
			"chance": 34.24
		},
		{
			"name": "Sir Valorcrest",
			"chance": 29.47,
			"killed": true
		},
		{
			"name": "Zushuka",
			"chance": 28.91
		},
		{
			"name": "Mr. Punish",
			"chance": 22.63,
			"killed": true
		},
		{
			"name": "Hairman the Huge",
			"chance": 21.96
		},
		{
			"name": "The Frog Prince",
			"chance": 20.86
		},
		{
			"name": "midnight panther",
			"chance": 17.32
		},
		{
			"name": "The Imperor",
			"chance": 16.53,
			"killed": true
		},
		{
			"name": "Fleabringer",
			"chance": 16.17
		},
		{
			"name": "Tyrn",
			"chance": 15.75
		},
		{
			"name": "Rukor Zad",
			"chance": 12.41
		},
		{
			"name": "Chizzoron the Distorter",
			"chance": 11.99
		},
		{
			"name": "Zulazza the Corruptor",
			"chance": 11.98
		},
		{
			"name": "Grand Mother Foulscale",
			"chance": 11.75
		},
		{
			"name": "High Templar Cobrass",
			"chance": 10.14
		},
		{
			"name": "Zomba",
			"chance": 9.23
		},
		{
			"name": "Flamecaller Zazrak",
			"chance": 6.45
		},
		{
			"name": "Battlemaster Zunzu",
			"chance": 4.97
		},
		{
			"name": "Morshabaal",
			"chance": 3.98
		},
		{
			"name": "The Voice of Ruin",
			"chance": 3.25
		},
		{
			"name": "Dreadmaw",
			"chance": 2.88
		},
		{
			"name": "Grorlam",
			"chance": 0,
			"killed": true
		},
		{
			"name": "Hatebreeder",
			"chance": 0,
			"killed": true
		},
		{
			"name": "Man in the Cave",
			"chance": 0,
			"killed": true
		},
		{
			"name": "Oodok Witchmaster",
			"chance": 0,
			"killed": true
		},
		{
			"name": "The Big Bad One",
			"chance": 0,
			"killed": true
		}
	]
}
