{
	"timestamp": "2024-03-02T03:33:15.573Z",
	"bosses": [
		{
			"name": "Willi Wasp",
			"chance": 39.41
		},
		{
			"name": "Zomba",
			"chance": 39.37,
			"killed": true
		},
		{
			"name": "Grand Mother Foulscale",
			"chance": 28.64
		},
		{
			"name": "The Blightfather",
			"chance": 23.41
		},
		{
			"name": "Hatebreeder",
			"chance": 22.13
		},
		{
			"name": "yeti",
			"chance": 21.65
		},
		{
			"name": "The Pale Count",
			"chance": 20.55,
			"killed": true
		},
		{
			"name": "Rukor Zad",
			"chance": 20.16
		},
		{
			"name": "Barbaria",
			"chance": 19.29
		},
		{
			"name": "midnight panther",
			"chance": 18.64
		},
		{
			"name": "Grandfather Tridian",
			"chance": 17.75
		},
		{
			"name": "Captain Jones",
			"chance": 17.43
		},
		{
			"name": "Sir Valorcrest",
			"chance": 16.18
		},
		{
			"name": "Ocyakao",
			"chance": 15.52
		},
		{
			"name": "The Voice of Ruin",
			"chance": 14.3
		},
		{
			"name": "Warlord Ruzad",
			"chance": 14.21
		},
		{
			"name": "Dreadmaw",
			"chance": 13.31
		},
		{
			"name": "Man in the Cave",
			"chance": 12.11
		},
		{
			"name": "The Old Whopper",
			"chance": 10.57,
			"killed": true
		},
		{
			"name": "Hirintror",
			"chance": 10.04
		},
		{
			"name": "Zushuka",
			"chance": 9.85,
			"killed": true
		},
		{
			"name": "Fleabringer",
			"chance": 9.51
		},
		{
			"name": "Flamecaller Zazrak",
			"chance": 9.47
		},
		{
			"name": "White Pale",
			"chance": 8.05
		},
		{
			"name": "Foreman Kneebiter",
			"chance": 6.75
		},
		{
			"name": "Tyrn",
			"chance": 6.5
		},
		{
			"name": "Orshabaal",
			"chance": 5.94
		},
		{
			"name": "Chizzoron the Distorter",
			"chance": 5.35
		},
		{
			"name": "Zulazza the Corruptor",
			"chance": 5.35
		},
		{
			"name": "Battlemaster Zunzu",
			"chance": 5.04
		},
		{
			"name": "Oodok Witchmaster",
			"chance": 0,
			"killed": true
		}
	]
}
