{
	"timestamp": "2023-09-16T02:33:54.377Z",
	"bosses": [
		{
			"name": "Grand Mother Foulscale",
			"chance": 27.99,
			"killed": true
		},
		{
			"name": "Tzumrah the Dazzler",
			"chance": 26.89,
			"killed": true
		},
		{
			"name": "The Evil Eye",
			"chance": 24.89
		},
		{
			"name": "Willi Wasp",
			"chance": 20.53
		},
		{
			"name": "Warlord Ruzad",
			"chance": 17.62
		},
		{
			"name": "Xenia",
			"chance": 16.21
		},
		{
			"name": "Sir Valorcrest",
			"chance": 15.97,
			"killed": true
		},
		{
			"name": "Chizzoron the Distorter",
			"chance": 13.69
		},
		{
			"name": "Zulazza the Corruptor",
			"chance": 13.69
		},
		{
			"name": "midnight panther",
			"chance": 13.24,
			"killed": true
		},
		{
			"name": "Fleabringer",
			"chance": 11.15
		},
		{
			"name": "Foreman Kneebiter",
			"chance": 10.3,
			"killed": true
		},
		{
			"name": "The Old Whopper",
			"chance": 9.97
		},
		{
			"name": "The Voice of Ruin",
			"chance": 9.83,
			"killed": true
		},
		{
			"name": "Hatebreeder",
			"chance": 9.74
		},
		{
			"name": "Barbaria",
			"chance": 8.77,
			"killed": true
		},
		{
			"name": "White Pale",
			"chance": 7.14
		},
		{
			"name": "Battlemaster Zunzu",
			"chance": 6.49
		},
		{
			"name": "Tyrn",
			"chance": 6.36
		},
		{
			"name": "Morshabaal",
			"chance": 4.16
		},
		{
			"name": "Hirintror",
			"chance": 3.24
		},
		{
			"name": "Flamecaller Zazrak",
			"chance": 3.07
		},
		{
			"name": "Dreadmaw",
			"chance": 2.82
		},
		{
			"name": "Arthom the Hunter",
			"chance": 0,
			"killed": true
		},
		{
			"name": "Burster",
			"chance": 0,
			"killed": true
		},
		{
			"name": "Groam",
			"chance": 0,
			"killed": true
		},
		{
			"name": "Grorlam",
			"chance": 0,
			"killed": true
		},
		{
			"name": "Oodok Witchmaster",
			"chance": 0,
			"killed": true
		},
		{
			"name": "draptor",
			"chance": 0,
			"killed": true
		}
	]
}
