{
	"timestamp": "2023-09-07T08:32:40.391Z",
	"bosses": [
		{
			"name": "Zomba",
			"chance": 62.03
		},
		{
			"name": "Shlorg",
			"chance": 38.38
		},
		{
			"name": "High Templar Cobrass",
			"chance": 31.07
		},
		{
			"name": "Mr. Punish",
			"chance": 28.6
		},
		{
			"name": "Massacre",
			"chance": 26.74
		},
		{
			"name": "Countess Sorrow",
			"chance": 23.77
		},
		{
			"name": "Xenia",
			"chance": 23.31
		},
		{
			"name": "Diblis the Fair",
			"chance": 21.82
		},
		{
			"name": "Big Boss Trolliver",
			"chance": 20.69
		},
		{
			"name": "Smuggler Baron Silvertoe",
			"chance": 20.26
		},
		{
			"name": "Warlord Ruzad",
			"chance": 17.51
		},
		{
			"name": "The Plasmother",
			"chance": 17.19
		},
		{
			"name": "midnight panther",
			"chance": 16.25
		},
		{
			"name": "Dracola",
			"chance": 12.55
		},
		{
			"name": "Omrafir",
			"chance": 11.77
		},
		{
			"name": "Fleabringer",
			"chance": 11.74
		},
		{
			"name": "Grand Mother Foulscale",
			"chance": 11.41
		},
		{
			"name": "The Welter",
			"chance": 11.17
		},
		{
			"name": "Willi Wasp",
			"chance": 11.14
		},
		{
			"name": "The Old Whopper",
			"chance": 9.96
		},
		{
			"name": "Hatebreeder",
			"chance": 9.8
		},
		{
			"name": "Dreadmaw",
			"chance": 9.08
		},
		{
			"name": "Gaz'haragoth",
			"chance": 9.06
		},
		{
			"name": "Barbaria",
			"chance": 8.53
		},
		{
			"name": "Tyrn",
			"chance": 8
		},
		{
			"name": "Foreman Kneebiter",
			"chance": 6.94
		},
		{
			"name": "White Pale",
			"chance": 6.54
		},
		{
			"name": "Battlemaster Zunzu",
			"chance": 5.32
		},
		{
			"name": "Ferumbras",
			"chance": 4.62
		},
		{
			"name": "Hirintror",
			"chance": 3.31
		},
		{
			"name": "Flamecaller Zazrak",
			"chance": 3.08
		},
		{
			"name": "The Voice of Ruin",
			"chance": 3.04
		}
	]
}
