{
	"timestamp": "2024-02-06T09:31:30.463Z",
	"bosses": [
		{
			"name": "Zomba",
			"chance": 39.37
		},
		{
			"name": "Zarabustor",
			"chance": 31.13
		},
		{
			"name": "Willi Wasp",
			"chance": 28.31
		},
		{
			"name": "The Frog Prince",
			"chance": 23.73
		},
		{
			"name": "Hairman the Huge",
			"chance": 20.49
		},
		{
			"name": "Yaga the Crone",
			"chance": 19.3
		},
		{
			"name": "Arachir the Ancient One",
			"chance": 18.81
		},
		{
			"name": "The Handmaiden",
			"chance": 17.68
		},
		{
			"name": "midnight panther",
			"chance": 17.21
		},
		{
			"name": "General Murius",
			"chance": 16.97
		},
		{
			"name": "Sir Valorcrest",
			"chance": 16.22
		},
		{
			"name": "Ghazbaran",
			"chance": 14.78
		},
		{
			"name": "The Evil Eye",
			"chance": 13.82
		},
		{
			"name": "Countess Sorrow",
			"chance": 13.3
		},
		{
			"name": "Shlorg",
			"chance": 12.87
		},
		{
			"name": "Grand Mother Foulscale",
			"chance": 11.55
		},
		{
			"name": "White Pale",
			"chance": 11.1
		},
		{
			"name": "yeti",
			"chance": 10.55
		},
		{
			"name": "Hatebreeder",
			"chance": 10.11
		},
		{
			"name": "Chizzoron the Distorter",
			"chance": 9.7
		},
		{
			"name": "Zulazza the Corruptor",
			"chance": 9.7
		},
		{
			"name": "Fleabringer",
			"chance": 9.26
		},
		{
			"name": "Flamecaller Zazrak",
			"chance": 9.06
		},
		{
			"name": "Battlemaster Zunzu",
			"chance": 6.62
		},
		{
			"name": "Massacre",
			"chance": 6.62
		},
		{
			"name": "Xenia",
			"chance": 5.81
		},
		{
			"name": "Tyrn",
			"chance": 4.88
		},
		{
			"name": "Hirintror",
			"chance": 4.03
		},
		{
			"name": "The Voice of Ruin",
			"chance": 3.1
		},
		{
			"name": "Dreadmaw",
			"chance": 2.14
		}
	]
}
