{
	"timestamp": "2025-09-23T09:34:14.245Z",
	"bosses": [
		{
			"name": "Arachir the Ancient One",
			"chance": 61.83
		},
		{
			"name": "Barbaria",
			"chance": 37.41
		},
		{
			"name": "The Plasmother",
			"chance": 36.91
		},
		{
			"name": "Tyrn",
			"chance": 28.65
		},
		{
			"name": "Zevelon Duskbringer",
			"chance": 27.64
		},
		{
			"name": "Mr. Punish",
			"chance": 22.68
		},
		{
			"name": "Big Boss Trolliver",
			"chance": 22.16
		},
		{
			"name": "Hairman the Huge",
			"chance": 22.13
		},
		{
			"name": "Zomba",
			"chance": 21.82
		},
		{
			"name": "Grand Mother Foulscale",
			"chance": 21.07
		},
		{
			"name": "Willi Wasp",
			"chance": 20.59
		},
		{
			"name": "Grandfather Tridian",
			"chance": 20.43
		},
		{
			"name": "Zarabustor",
			"chance": 18.04
		},
		{
			"name": "Sir Valorcrest",
			"chance": 16.05
		},
		{
			"name": "Flamecaller Zazrak",
			"chance": 14.08
		},
		{
			"name": "Foreman Kneebiter",
			"chance": 13.02
		},
		{
			"name": "Shlorg",
			"chance": 12.96
		},
		{
			"name": "Omrafir",
			"chance": 11.55
		},
		{
			"name": "Zushuka",
			"chance": 9.68
		},
		{
			"name": "Hirintror",
			"chance": 9.09
		},
		{
			"name": "Yaga the Crone",
			"chance": 8.86
		},
		{
			"name": "Fleabringer",
			"chance": 8.1
		},
		{
			"name": "The Big Bad One",
			"chance": 7.69
		},
		{
			"name": "White Pale",
			"chance": 7.29
		},
		{
			"name": "Battlemaster Zunzu",
			"chance": 6.57
		},
		{
			"name": "Dreadmaw",
			"chance": 3.57
		},
		{
			"name": "The Voice of Ruin",
			"chance": 3.25
		}
	]
}
