{
	"timestamp": "2025-05-01T03:45:58.426Z",
	"bosses": [
		{
			"name": "Diblis the Fair",
			"chance": 71.96,
			"killed": true
		},
		{
			"name": "General Murius",
			"chance": 33.83,
			"killed": true
		},
		{
			"name": "Ocyakao",
			"chance": 22.72
		},
		{
			"name": "Big Boss Trolliver",
			"chance": 21.99,
			"killed": true
		},
		{
			"name": "Grand Mother Foulscale",
			"chance": 21.16
		},
		{
			"name": "Battlemaster Zunzu",
			"chance": 20.94
		},
		{
			"name": "Foreman Kneebiter",
			"chance": 20.92
		},
		{
			"name": "Arachir the Ancient One",
			"chance": 19.07
		},
		{
			"name": "The Old Whopper",
			"chance": 18.23
		},
		{
			"name": "midnight panther",
			"chance": 17.6,
			"killed": true
		},
		{
			"name": "Sir Valorcrest",
			"chance": 16.05
		},
		{
			"name": "Flamecaller Zazrak",
			"chance": 13.51
		},
		{
			"name": "Countess Sorrow",
			"chance": 13.3,
			"killed": true
		},
		{
			"name": "Gravelord Oshuran",
			"chance": 13.06
		},
		{
			"name": "Hairman the Huge",
			"chance": 12.65
		},
		{
			"name": "Hirintror",
			"chance": 10.82
		},
		{
			"name": "Warlord Ruzad",
			"chance": 10.8
		},
		{
			"name": "The Welter",
			"chance": 9.2
		},
		{
			"name": "Fleabringer",
			"chance": 8.93,
			"killed": true
		},
		{
			"name": "The Pale Count",
			"chance": 8.47
		},
		{
			"name": "Chizzoron the Distorter",
			"chance": 8.31
		},
		{
			"name": "Zulazza the Corruptor",
			"chance": 8.3
		},
		{
			"name": "Tyrn",
			"chance": 8.09,
			"killed": true
		},
		{
			"name": "Dracola",
			"chance": 7.03
		},
		{
			"name": "White Pale",
			"chance": 6.69
		},
		{
			"name": "Xenia",
			"chance": 5.72
		},
		{
			"name": "The Voice of Ruin",
			"chance": 3.21
		},
		{
			"name": "Dreadmaw",
			"chance": 3.09
		},
		{
			"name": "Arthom the Hunter",
			"chance": 0,
			"killed": true
		},
		{
			"name": "Cublarc the Plunderer",
			"chance": 0,
			"killed": true
		}
	]
}
