{
	"timestamp": "2026-05-03T03:06:18.376Z",
	"bosses": [
		{
			"name": "Sir Valorcrest",
			"chance": 42.53
		},
		{
			"name": "Arachir the Ancient One",
			"chance": 38.04
		},
		{
			"name": "Big Boss Trolliver",
			"chance": 29.59
		},
		{
			"name": "Zevelon Duskbringer",
			"chance": 27.69
		},
		{
			"name": "The Imperor",
			"chance": 25.9
		},
		{
			"name": "The Old Whopper",
			"chance": 22.45,
			"killed": true
		},
		{
			"name": "Rukor Zad",
			"chance": 21.09
		},
		{
			"name": "Foreman Kneebiter",
			"chance": 18.62
		},
		{
			"name": "Diblis the Fair",
			"chance": 17.81,
			"killed": true
		},
		{
			"name": "Mr. Punish",
			"chance": 15.77,
			"killed": true
		},
		{
			"name": "Massacre",
			"chance": 15.74
		},
		{
			"name": "Fleabringer",
			"chance": 13.95,
			"killed": true
		},
		{
			"name": "Omrafir",
			"chance": 11.57
		},
		{
			"name": "Willi Wasp",
			"chance": 11.27
		},
		{
			"name": "Hatebreeder",
			"chance": 10.87,
			"killed": true
		},
		{
			"name": "White Pale",
			"chance": 7.33
		},
		{
			"name": "The Frog Prince",
			"chance": 6.48
		},
		{
			"name": "Tyrn",
			"chance": 5.36
		},
		{
			"name": "Battlemaster Zunzu",
			"chance": 4.95
		},
		{
			"name": "Flamecaller Zazrak",
			"chance": 4.75
		},
		{
			"name": "Orshabaal",
			"chance": 4.55
		},
		{
			"name": "The Voice of Ruin",
			"chance": 4.04
		},
		{
			"name": "Hirintror",
			"chance": 3.64
		},
		{
			"name": "Dreadmaw",
			"chance": 3.04
		},
		{
			"name": "Groam",
			"chance": 0,
			"killed": true
		},
		{
			"name": "Yakchal",
			"chance": 0,
			"killed": true
		}
	]
}
