{
	"timestamp": "2026-02-20T04:16:12.097Z",
	"bosses": [
		{
			"name": "The Blightfather",
			"chance": 46.6
		},
		{
			"name": "Dharalion",
			"chance": 31.9,
			"killed": true
		},
		{
			"name": "Diblis the Fair",
			"chance": 29.85
		},
		{
			"name": "Rukor Zad",
			"chance": 29.65
		},
		{
			"name": "yeti",
			"chance": 27.61
		},
		{
			"name": "Foreman Kneebiter",
			"chance": 19.8
		},
		{
			"name": "Hairman the Huge",
			"chance": 15.96
		},
		{
			"name": "The Evil Eye",
			"chance": 15.01
		},
		{
			"name": "The Imperor",
			"chance": 13.18
		},
		{
			"name": "Gravelord Oshuran",
			"chance": 11.31
		},
		{
			"name": "Xenia",
			"chance": 11.23
		},
		{
			"name": "Hatebreeder",
			"chance": 10.7,
			"killed": true
		},
		{
			"name": "White Pale",
			"chance": 9.27
		},
		{
			"name": "Omrafir",
			"chance": 8.77
		},
		{
			"name": "The Pale Count",
			"chance": 8.47
		},
		{
			"name": "The Voice of Ruin",
			"chance": 8.39
		},
		{
			"name": "Fleabringer",
			"chance": 8.27
		},
		{
			"name": "The Big Bad One",
			"chance": 7.75
		},
		{
			"name": "Shlorg",
			"chance": 7.26
		},
		{
			"name": "Countess Sorrow",
			"chance": 7.06
		},
		{
			"name": "The Old Whopper",
			"chance": 6.82
		},
		{
			"name": "Battlemaster Zunzu",
			"chance": 6.51
		},
		{
			"name": "Ocyakao",
			"chance": 6.11
		},
		{
			"name": "Tyrn",
			"chance": 5.48,
			"killed": true
		},
		{
			"name": "Flamecaller Zazrak",
			"chance": 4.34
		},
		{
			"name": "Dreadmaw",
			"chance": 3.42
		},
		{
			"name": "Hirintror",
			"chance": 3.3
		},
		{
			"name": "Cublarc the Plunderer",
			"chance": 0,
			"killed": true
		}
	]
}
