{
	"timestamp": "2026-06-07T03:08:55.710Z",
	"bosses": [
		{
			"name": "Big Boss Trolliver",
			"chance": 0,
			"killed": true
		},
		{
			"name": "Burster",
			"chance": 0,
			"killed": true
		},
		{
			"name": "Fleabringer",
			"chance": 0,
			"killed": true
		},
		{
			"name": "General Murius",
			"chance": 0,
			"killed": true
		},
		{
			"name": "Grorlam",
			"chance": 0,
			"killed": true
		},
		{
			"name": "Hairman the Huge",
			"chance": 0,
			"killed": true
		},
		{
			"name": "Massacre",
			"chance": 0,
			"killed": true
		},
		{
			"name": "The Evil Eye",
			"chance": 0,
			"killed": true
		},
		{
			"name": "The Welter",
			"chance": 0,
			"killed": true
		}
	]
}
